MANIFEST.in
README.md
setup.py
lib/PostCodeClient.py
lib/__init__.py
postcode.io.egg-info/PKG-INFO
postcode.io.egg-info/SOURCES.txt
postcode.io.egg-info/dependency_links.txt
postcode.io.egg-info/requires.txt
postcode.io.egg-info/top_level.txt
test/test.py