Metadata-Version: 1.0
Name: postcode.io
Version: 0.1.1
Summary: Postcode & Geolocation API for UK for python
Home-page: https://github.com/previousdeveloper/PythonPostcodesWrapper
Author: Gokhan Karadas
Author-email: gokhan.karadas1992@gmail.com
License: LICENSE
Download-URL: https://github.com/previousdeveloper/PythonPostcodesWrapper
Platform: UNKNOWN
